COPYING
COPYING.LESSER
MANIFEST.in
README.rst
SConstruct
VERSION
requirements.setup.txt
requirements.txt
setup.cfg
setup.py
test.cpp
zetuprc
./PREFIX
./VERSION
./__init__.py
./libcfo.py
./requirements.txt
carefree_objects.egg-info/PKG-INFO
carefree_objects.egg-info/SOURCES.txt
carefree_objects.egg-info/dependency_links.txt
carefree_objects.egg-info/requires.txt
carefree_objects.egg-info/top_level.txt
cfo/__init__.py
cfo/zetup_config.py
cfo/jinja/__init__.py
cfo/jinja/context.py
cfo/jinja/types.py
cfo/jinja/macros/__init__.py
cfo/jinja/macros/cfo
cfo/pkg/__init__.py
cfo/scons/__init__.py
cfo/scons/vars.py
src/__init__.py
src/bits.cpp
src/context.py
src/ip.cpp
src/include/carefree-objects.hpp
src/include/carefree-python.hpp
src/include/carefree-types.hpp
src/include/carefree-objects/accessor.hpp
src/include/carefree-objects/basic_manager.hpp
src/include/carefree-objects/common.hpp
src/include/carefree-objects/const_accessor.hpp
src/include/carefree-objects/const_methods.hpp
src/include/carefree-objects/count_and_lock.hpp
src/include/carefree-objects/error.hpp
src/include/carefree-objects/forward.hpp
src/include/carefree-objects/managed.hpp
src/include/carefree-objects/map.hpp
src/include/carefree-objects/methods.hpp
src/include/carefree-objects/vector.hpp
src/include/carefree-python/common.hpp
src/include/carefree-python/convert.hpp
src/include/carefree-python/except.hpp
src/include/carefree-python/extract.hpp
src/include/carefree-python/functions.hpp
src/include/carefree-python/import.hpp
src/include/carefree-python/object.hpp
src/include/carefree-python/object.inl
src/include/carefree-python/object/iterator.hpp
src/include/carefree-types/bits.hpp
src/include/carefree-types/bits.inl
src/include/carefree-types/byteorder.inl
src/include/carefree-types/bytes.hpp
src/include/carefree-types/c_array.hpp
src/include/carefree-types/c_string.hpp
src/include/carefree-types/common.hpp
src/include/carefree-types/ip.hpp
src/include/carefree-types/mac.hpp
src/include/carefree-types/named.hpp
src/include/carefree-types/string.hpp
src/include/carefree-types/ip/address.hpp
src/include/carefree-types/ip/v4.hpp
src/include/carefree-types/ip/v6.hpp
