Metadata-Version: 1.1
Name: carefree-objects
Version: 0.1
Summary: A managed object framework for C++ and Python extensions
Home-page: http://bitbucket.org/userzimmermann/carefree-objects
Author: Stefan Zimmermann
Author-email: zimmermann.code@gmail.com
License: LGPLv3
Platform: UNKNOWN
Classifier: Programming Language :: Python
Classifier: Programming Language :: Python :: 2.7
